pytest_asyncio_network_simulator/__init__.py
pytest_asyncio_network_simulator/address.py
pytest_asyncio_network_simulator/host.py
pytest_asyncio_network_simulator/network.py
pytest_asyncio_network_simulator/plugin.py
pytest_asyncio_network_simulator/router.py
pytest_asyncio_network_simulator/server.py
pytest_asyncio_network_simulator/streams.py
pytest_asyncio_network_simulator/transports.py
pytest_asyncio_network_simulator/utils.py
pytest_asyncio_network_simulator-0.1.0a2.dist-info/METADATA
pytest_asyncio_network_simulator-0.1.0a2.dist-info/RECORD
pytest_asyncio_network_simulator-0.1.0a2.dist-info/WHEEL
pytest_asyncio_network_simulator-0.1.0a2.dist-info/entry_points.txt
pytest_asyncio_network_simulator-0.1.0a2.dist-info/top_level.txt
