Metadata-Version: 2.1
Name: pytest-asyncio-network-simulator
Version: 0.1.0a2
Summary: pytest-asyncio-network-simulator: Plugin for pytest for simulator the network in tests
Home-page: https://github.com/ethereum/pytest-asyncio-network-simulator
Author: Ethereum Foundation
Author-email: piper@pipermerriam.com
License: MIT
Keywords: asyncio network pytest
Platform: UNKNOWN
Classifier: Development Status :: 3 - Alpha
Classifier: Intended Audience :: Developers
Classifier: License :: OSI Approved :: MIT License
Classifier: Natural Language :: English
Classifier: Programming Language :: Python :: 3
Classifier: Programming Language :: Python :: 3.6
Classifier: Programming Language :: Python :: 3.7
Requires-Python: >=3.6, <4
Provides-Extra: test
Provides-Extra: doc
Provides-Extra: dev
Provides-Extra: lint
Requires-Dist: asyncio-cancel-token (==0.1.0a2)
Requires-Dist: pytest (<3.7.0,>=3.3.2)
Requires-Dist: pytest-asyncio (<1,>=0.8.0)
Provides-Extra: dev
Requires-Dist: bumpversion (<1,>=0.5.3); extra == 'dev'
Requires-Dist: pytest-watch (<5,>=4.1.0); extra == 'dev'
Requires-Dist: wheel; extra == 'dev'
Requires-Dist: twine; extra == 'dev'
Requires-Dist: ipython; extra == 'dev'
Requires-Dist: pytest (==3.3.2); extra == 'dev'
Requires-Dist: pytest-xdist; extra == 'dev'
Requires-Dist: pytest-asyncio (==0.8.0); extra == 'dev'
Requires-Dist: tox (<3,>=2.9.1); extra == 'dev'
Requires-Dist: flake8 (==3.4.1); extra == 'dev'
Requires-Dist: isort (<5,>=4.2.15); extra == 'dev'
Requires-Dist: mypy (==0.610); extra == 'dev'
Requires-Dist: Sphinx (<2,>=1.6.5); extra == 'dev'
Requires-Dist: sphinx-rtd-theme (>=0.1.9); extra == 'dev'
Provides-Extra: doc
Requires-Dist: Sphinx (<2,>=1.6.5); extra == 'doc'
Requires-Dist: sphinx-rtd-theme (>=0.1.9); extra == 'doc'
Provides-Extra: lint
Requires-Dist: flake8 (==3.4.1); extra == 'lint'
Requires-Dist: isort (<5,>=4.2.15); extra == 'lint'
Requires-Dist: mypy (==0.610); extra == 'lint'
Provides-Extra: test
Requires-Dist: pytest (==3.3.2); extra == 'test'
Requires-Dist: pytest-xdist; extra == 'test'
Requires-Dist: pytest-asyncio (==0.8.0); extra == 'test'
Requires-Dist: tox (<3,>=2.9.1); extra == 'test'
